todoist_cli/__init__.py
todoist_cli/cli.py
todoist_cli/client.py
todoist_cli/tempCodeRunnerFile.py
todoist_cli/commands/__init__.py
todoist_cli/commands/add.py
todoist_cli/commands/delete.py
todoist_cli/commands/list_task.py
todoist_cli/commands/sync.py
todoist_cli/models/__init__.py
todoist_cli/models/label.py
todoist_cli/models/project.py
todoist_cli/models/task.py
todoist_cli/utils/__init__.py
todoist_cli/utils/cache.py
todoist_cli/utils/catppuccin_theme.py
todoist_cli/utils/config.py
todoist_cli/utils/date_utils.py
todoist_cli/utils/ui_theme.py
cli_tool_for_todoist-0.4.dist-info/LICENSE
cli_tool_for_todoist-0.4.dist-info/METADATA
cli_tool_for_todoist-0.4.dist-info/WHEEL
cli_tool_for_todoist-0.4.dist-info/entry_points.txt
cli_tool_for_todoist-0.4.dist-info/top_level.txt
cli_tool_for_todoist-0.4.dist-info/RECORD
